.gitignore
LICENSE
MANIFEST.in
NOTICES
README.rst
setup.py
loomengine/.gitignore
loomengine/VERSION
loomengine/__init__.py
loomengine/auth.py
loomengine/browser.py
loomengine/bulk_import.py
loomengine/common.py
loomengine/example.py
loomengine/file_client.py
loomengine/file_label.py
loomengine/file_tag.py
loomengine/main.py
loomengine/run.py
loomengine/run_label.py
loomengine/run_tag.py
loomengine/server.py
loomengine/template.py
loomengine/template_label.py
loomengine/template_tag.py
loomengine/test_runner.py
loomengine/user.py
loomengine.egg-info/PKG-INFO
loomengine.egg-info/SOURCES.txt
loomengine.egg-info/dependency_links.txt
loomengine.egg-info/entry_points.txt
loomengine.egg-info/requires.txt
loomengine.egg-info/top_level.txt
loomengine/examples/add_then_multiply/README.txt
loomengine/examples/add_then_multiply/add_then_multiply.yaml
loomengine/examples/building_blocks/README.txt
loomengine/examples/building_blocks/building_blocks.yaml
loomengine/examples/building_blocks/building_blocks.yaml.dependencies/templates/add.yaml
loomengine/examples/building_blocks/building_blocks.yaml.dependencies/templates/multiply.yaml
loomengine/examples/capitalize_words/README.txt
loomengine/examples/capitalize_words/capitalize_words.yaml
loomengine/examples/hello_world/README.txt
loomengine/examples/hello_world/hello_world.yaml
loomengine/examples/hello_world/hello_world.yaml.dependencies/files/hello.txt
loomengine/examples/hello_world/hello_world.yaml.dependencies/files/world.txt
loomengine/examples/join_array_of_words/README.txt
loomengine/examples/join_array_of_words/join_array_of_words.yaml
loomengine/examples/join_two_words/README.txt
loomengine/examples/join_two_words/join_two_words.yaml
loomengine/examples/search_file/README.txt
loomengine/examples/search_file/beowulf.txt
loomengine/examples/search_file/search_file.yaml
loomengine/examples/search_file/search_file.yaml.dependencies/files/lorem_ipsum.txt
loomengine/examples/sentence_scoring/README.txt
loomengine/examples/sentence_scoring/sentence_scoring.yaml
loomengine/examples/split_words_into_array/README.txt
loomengine/examples/split_words_into_array/split_words_into_array.yaml
